aimsim/__init__.py
aimsim/__main__.py
aimsim/exceptions.py
aimsim/chemical_datastructures/__init__.py
aimsim/chemical_datastructures/molecule.py
aimsim/chemical_datastructures/molecule_set.py
aimsim/ops/__init__.py
aimsim/ops/clustering.py
aimsim/ops/descriptor.py
aimsim/ops/similarity_measures.py
aimsim/tasks/__init__.py
aimsim/tasks/cluster_data.py
aimsim/tasks/compare_target_molecule.py
aimsim/tasks/extended_similarity_indices.py
aimsim/tasks/identify_outliers.py
aimsim/tasks/measure_search.py
aimsim/tasks/see_property_variation_with_similarity.py
aimsim/tasks/task.py
aimsim/tasks/task_manager.py
aimsim/tasks/visualize_dataset.py
aimsim/utils/__init__.py
aimsim/utils/ccbmlib_fingerprints.py
aimsim/utils/plotting_scripts.py
aimsim-2.2.3.dist-info/licenses/LICENSE
interfaces/__init__.py
interfaces/config_reader.py
interfaces/UI/AIMSim-GUI-corner-logo.png
interfaces/UI/AIMSim-logo.png
interfaces/UI/AIMSim_ui_main.py
interfaces/UI/__init__.py
interfaces/UI/libraries/README.md
aimsim-2.2.3.dist-info/METADATA
aimsim-2.2.3.dist-info/WHEEL
aimsim-2.2.3.dist-info/entry_points.txt
aimsim-2.2.3.dist-info/top_level.txt
aimsim-2.2.3.dist-info/RECORD
