Metadata-Version: 2.4
Name: aimsim
Version: 2.2.3
Summary: Python command line and GUI tool to analyze molecular similarity.
Home-page: https://github.com/VlachosGroup/AIMSim
Author: Himaghna Bhattacharjee, Jackson Burns
License: MIT
Classifier: Programming Language :: Python :: 3
Requires-Python: >=3.8
License-File: LICENSE
Requires-Dist: scipy
Requires-Dist: matplotlib
Requires-Dist: seaborn
Requires-Dist: tabulate
Requires-Dist: numpy
Requires-Dist: multiprocess>=0.70
Requires-Dist: pandas
Requires-Dist: pyyaml!=5.4.0,!=5.4.1,!=6.0.0,<7
Requires-Dist: scikit_learn
Requires-Dist: rdkit
Requires-Dist: psutil
Requires-Dist: padelpy
Requires-Dist: plotly
Requires-Dist: mhfp
Requires-Dist: darkdetect
Requires-Dist: mordredcommunity
Requires-Dist: openpyxl
Dynamic: author
Dynamic: classifier
Dynamic: description
Dynamic: description-content-type
Dynamic: home-page
Dynamic: license
Dynamic: license-file
Dynamic: requires-dist
Dynamic: requires-python
Dynamic: summary
